info/gianlucacosta/iris/__init__.py
info/gianlucacosta/iris/io/__init__.py
info/gianlucacosta/iris/io/filetree.py
info/gianlucacosta/iris/io/utils.py
info/gianlucacosta/iris/ioc.py
info/gianlucacosta/iris/maven.py
info/gianlucacosta/iris/rendering.py
info/gianlucacosta/iris/scripts/__init__.py
info/gianlucacosta/iris/scripts/rmheader.py
info/gianlucacosta/iris/scripts/rmlicense.py
info/gianlucacosta/iris/scripts/rmspaces.py
info/gianlucacosta/iris/vars.py
info/gianlucacosta/iris/versioning.py
info.gianlucacosta.iris-4.0.1.dist-info/entry_points.txt
info.gianlucacosta.iris-4.0.1.dist-info/LICENSE
info.gianlucacosta.iris-4.0.1.dist-info/WHEEL
info.gianlucacosta.iris-4.0.1.dist-info/METADATA
info.gianlucacosta.iris-4.0.1.dist-info/RECORD
