Metadata-Version: 2.1
Name: info.gianlucacosta.iris
Version: 4.0.1
Summary: General-purpose library for Python
Home-page: https://github.com/giancosta86/Iris
License: LGPLv3
Keywords: library,IoC container,dependency injector,versioning,Maven,rendering,utilities
Author: Gianluca Costa
Author-email: gianluca@gianlucacosta.info
Requires-Python: >=3.6.2,<4.0.0
Classifier: Development Status :: 5 - Production/Stable
Classifier: Intended Audience :: Developers
Classifier: License :: OSI Approved :: GNU Lesser General Public License v3 (LGPLv3)
Classifier: License :: Other/Proprietary License
Classifier: Operating System :: OS Independent
Classifier: Programming Language :: Python
Classifier: Programming Language :: Python :: 3
Classifier: Programming Language :: Python :: 3.10
Classifier: Programming Language :: Python :: 3.7
Classifier: Programming Language :: Python :: 3.8
Classifier: Programming Language :: Python :: 3.9
Classifier: Topic :: Utilities
Project-URL: Documentation, https://github.com/giancosta86/Iris
Project-URL: Repository, https://github.com/giancosta86/Iris
